lila/__init__.py
lila/config.py
lila/const.py
lila/main.py
lila/runner.py
lila/utils.py
lila/version.py
lila/assets/env
lila/assets/gitignore
lila/assets/google-maps.yaml
lila/assets/lila.toml
lila/assets/report.html
lilacli-0.1.13.dist-info/METADATA
lilacli-0.1.13.dist-info/WHEEL
lilacli-0.1.13.dist-info/entry_points.txt
lilacli-0.1.13.dist-info/RECORD
