Metadata-Version: 2.4
Name: lilacli
Version: 0.1.13
Summary: A CLI for lila.dev
Project-URL: Homepage, https://lila.dev
Requires-Python: >=3.11
Requires-Dist: browser-use~=0.1.36
Requires-Dist: click
Requires-Dist: dacite
Requires-Dist: jinja2
Requires-Dist: loguru
Requires-Dist: playwright
Requires-Dist: python-dotenv~=1.0
Requires-Dist: pyyaml
Requires-Dist: requests
Requires-Dist: tenacity
